{
  "rdbms": {
    "MYSQL": {
      "databaseName": "model",
      "pluginId": "MYSQL",
      "accessType": 0,
      "hostname": "103.82.93.55",
      "password": "Encrypted ",
      "pluginName": "MySQL",
      "port": "9030",
      "driverClassName": "Mysql 8+",
      "attributes": {
        "SUPPORTS_TIMESTAMP_DATA_TYPE": "N",
        "STREAM_RESULTS": "N",
        "EXTRA_OPTION_MYSQL.useCursorFetch": "true",
        "EXTRA_OPTION_MYSQL.defaultFetchSize": "500",
        "FORCE_IDENTIFIERS_TO_LOWERCASE": "N",
        "PRESERVE_RESERVED_WORD_CASE": "Y",
        "FORCE_IDENTIFIERS_TO_UPPERCASE": "N",
        "QUOTE_ALL_FIELDS": "N",
        "EXTRA_OPTION_MYSQL.zeroDateTimeBehaviorValue": "CONVERT_TO_NULL",
        "SUPPORTS_BOOLEAN_DATA_TYPE": "Y",
        "SQL_CONNECT": "",
        "PREFERRED_SCHEMA_NAME": ""
      },
      "manualUrl": "",
      "username": "root"
    }
  },
  "name": "modelDoris"
}